Metadata-Version: 2.1
Name: johnsnowlabs
Version: 6.2.0
Summary: The John Snow Labs Library gives you access to all of John Snow Labs Enterprise And Open Source products in an easy and simple manner. Access 10000+ state-of-the-art NLP and OCR models for Finance, Legal and Medical domains. Easily scalable to Spark Cluster 
Home-page: https://www.johnsnowlabs.com/
Author: John Snow Labs
Author-email: christian@johnsnowlabs.com
License: UNKNOWN
Keywords: Spark NLP OCR Finance Legal Medical John Snow Labs
Platform: UNKNOWN
Classifier: Development Status :: 5 - Production/Stable
Classifier: Intended Audience :: Developers
Classifier: Topic :: Software Development :: Build Tools
Classifier: License :: OSI Approved :: Apache Software License
Classifier: Programming Language :: Python :: 3
Classifier: Programming Language :: Python :: 3.7
Classifier: Programming Language :: Python :: 3.8
Classifier: Programming Language :: Python :: 3.9
Classifier: Programming Language :: Python :: 3.10
Classifier: Programming Language :: Python :: 3.11
Requires-Dist: pyspark==3.4.0
Requires-Dist: spark-nlp==6.2.0
Requires-Dist: nlu==5.4.1
Requires-Dist: spark-nlp-display==5.0
Requires-Dist: numpy
Requires-Dist: dataclasses
Requires-Dist: requests
Requires-Dist: databricks-api
Requires-Dist: pydantic>=2
Requires-Dist: colorama
Requires-Dist: boto3
